airbase/__init__.py
airbase/__version__.py
airbase/airbase.py
airbase/cli.py
airbase/fetch.py
airbase/resources.py
airbase/util.py
airbase/summary/__init__.py
airbase/summary/db.py
airbase/summary/summary.sqlite
airbase-0.8.1.dist-info/LICENSE
airbase-0.8.1.dist-info/METADATA
airbase-0.8.1.dist-info/WHEEL
airbase-0.8.1.dist-info/entry_points.txt
airbase-0.8.1.dist-info/top_level.txt
airbase-0.8.1.dist-info/RECORD
