Metadata-Version: 2.1
Name: airbase
Version: 0.8.1
Summary: An easy downloader for the AirBase air quality data.
Home-page: https://github.com/johnpaton/airbase
Author: John Paton
License: MIT
Classifier: License :: OSI Approved :: MIT License
Classifier: Programming Language :: Python
Classifier: Programming Language :: Python :: 3
Classifier: Programming Language :: Python :: 3.8
Classifier: Programming Language :: Python :: 3.9
Classifier: Programming Language :: Python :: 3.10
Classifier: Programming Language :: Python :: 3.11
Classifier: Programming Language :: Python :: 3.12
Classifier: Intended Audience :: Science/Research
Classifier: Topic :: Scientific/Engineering
Classifier: Topic :: Scientific/Engineering :: Atmospheric Science
Requires-Python: <4,>=3.8
License-File: LICENSE
Requires-Dist: aiofiles
Requires-Dist: tqdm
Requires-Dist: typer>=0.9.1
Requires-Dist: importlib-resources; python_version < "3.11"
Requires-Dist: aiohttp; python_version < "3.12"
Requires-Dist: aiohttp>=3.9.0; python_version >= "3.12"
Provides-Extra: docs
Requires-Dist: sphinx>=4.2.0; extra == "docs"
Requires-Dist: sphinx-rtd-theme; extra == "docs"
Requires-Dist: importlib-metadata; python_version < "3.8" and extra == "docs"
Provides-Extra: test
Requires-Dist: pytest>=6.0; extra == "test"
Requires-Dist: aioresponses; extra == "test"
Requires-Dist: pytest-cov; extra == "test"
